{
  "providers": {
    "awscloudformation": {
      "AuthRoleName": "amplify-pronto-dev-163054-authRole",
      "UnauthRoleArn": "arn:aws:iam::915206092794:role/amplify-pronto-dev-163054-unauthRole",
      "AuthRoleArn": "arn:aws:iam::915206092794:role/amplify-pronto-dev-163054-authRole",
      "Region": "us-east-1",
      "DeploymentBucketName": "amplify-pronto-dev-163054-deployment",
      "UnauthRoleName": "amplify-pronto-dev-163054-unauthRole",
      "StackName": "amplify-pronto-dev-163054",
      "StackId": "arn:aws:cloudformation:us-east-1:915206092794:stack/amplify-pronto-dev-163054/3aaa7e80-19ae-11ee-8eb8-0a7f71ca4217",
      "AmplifyAppId": "d3j57fmadrzn3",
      "AuthTriggerTemplateURL": "https://s3.amazonaws.com/amplify-pronto-dev-163054-deployment/amplify-cfn-templates/auth/auth-trigger-cloudformation-template.json"
    }
  },
  "analytics": {
    "prontoEmailNotifications": {
      "providerPlugin": "awscloudformation",
      "service": "Pinpoint",
      "output": {
        "appName": "prontoEmailNotifications-dev",
        "Region": "us-east-1",
        "Id": "e3ee422b4dff46b1845dfbe5b80d82e5"
      },
      "lastPushTimeStamp": "2023-09-01T21:24:42.708Z",
      "providerMetadata": {
        "s3TemplateURL": "https://s3.amazonaws.com/amplify-pronto-dev-163054-deployment/amplify-cfn-templates/analytics/pinpoint-cloudformation-template.json",
        "logicalId": "analyticsprontoEmailNotifications"
      }
    }
  },
  "api": {
    "AdminQueries": {
      "authorizationType": "AMAZON_COGNITO_USER_POOLS",
      "dependsOn": [
        {
          "attributes": [
            "UserPoolId"
          ],
          "category": "auth",
          "resourceName": "pronto5f713f59"
        },
        {
          "attributes": [
            "Arn",
            "Name"
          ],
          "category": "function",
          "resourceName": "AdminQueries7f7a03b0"
        }
      ],
      "providerPlugin": "awscloudformation",
      "service": "API Gateway",
      "output": {
        "ApiName": "AdminQueries",
        "RootUrl": "https://5t7q1hxeo1.execute-api.us-east-1.amazonaws.com/dev",
        "ApiId": "5t7q1hxeo1"
      },
      "lastPushTimeStamp": "2023-09-01T21:24:42.711Z",
      "providerMetadata": {
        "s3TemplateURL": "https://s3.amazonaws.com/amplify-pronto-dev-163054-deployment/amplify-cfn-templates/api/AdminQueries-cloudformation-template.json",
        "logicalId": "apiAdminQueries"
      }
    },
    "pronto": {
      "dependsOn": [
        {
          "attributes": [
            "UserPoolId"
          ],
          "category": "auth",
          "resourceName": "pronto5f713f59"
        }
      ],
      "output": {
        "authConfig": {
          "additionalAuthenticationProviders": [
            {
              "apiKeyConfig": {
                "apiKeyExpirationDate": "2023-08-14T06:43:37.483Z",
                "apiKeyExpirationDays": 30,
                "description": "GraphQL API Key"
              },
              "authenticationType": "API_KEY"
            }
          ],
          "defaultAuthentication": {
            "authenticationType": "AMAZON_COGNITO_USER_POOLS",
            "userPoolConfig": {
              "userPoolId": "authpronto5f713f59"
            }
          }
        },
        "GraphQLAPIIdOutput": "dytoellbofcrpnwlehbeo4ikbe",
        "GraphQLAPIEndpointOutput": "https://ixpdvfhkcngzlnldxtrnfp22ye.appsync-api.us-east-1.amazonaws.com/graphql",
        "GraphQLAPIKeyOutput": "da2-qwh465ynhrbtdj4uxdvqflyu6m"
      },
      "providerPlugin": "awscloudformation",
      "service": "AppSync",
      "lastPushTimeStamp": "2023-09-01T21:24:42.712Z",
      "providerMetadata": {
        "s3TemplateURL": "https://s3.amazonaws.com/amplify-pronto-dev-163054-deployment/amplify-cfn-templates/api/cloudformation-template.json",
        "logicalId": "apipronto"
      }
    }
  },
  "auth": {
    "pronto5f713f59": {
      "customAuth": false,
      "dependsOn": [
        {
          "attributes": [
            "Arn",
            "Name"
          ],
          "category": "function",
          "resourceName": "pronto5f713f59PostAuthentication",
          "triggerProvider": "Cognito"
        },
        {
          "attributes": [
            "Arn",
            "Name"
          ],
          "category": "function",
          "resourceName": "pronto5f713f59PreSignup",
          "triggerProvider": "Cognito"
        }
      ],
      "frontendAuthConfig": {
        "mfaConfiguration": "OFF",
        "mfaTypes": [
          "SMS"
        ],
        "passwordProtectionSettings": {
          "passwordPolicyMinLength": 8,
          "passwordPolicyCharacters": []
        },
        "signupAttributes": [
          "EMAIL",
          "FAMILY_NAME",
          "NAME"
        ],
        "socialProviders": [],
        "usernameAttributes": [
          "EMAIL"
        ],
        "verificationMechanisms": [
          "EMAIL"
        ]
      },
      "providerPlugin": "awscloudformation",
      "service": "Cognito",
      "output": {
        "UserPoolId": "us-east-1_0MFceeZ4B",
        "AppClientIDWeb": "j9shrouag9o2appmrjvfgtm75",
        "AppClientID": "67lg7el40kvcb1rkrjv8ghdo5h",
        "IdentityPoolId": "us-east-1:21c73461-07a0-429d-96c1-f98c711cdef8",
        "UserPoolArn": "arn:aws:cognito-idp:us-east-1:915206092794:userpool/us-east-1_0MFceeZ4B",
        "IdentityPoolName": "pronto5f713f59_identitypool_5f713f59__dev",
        "UserPoolName": "pronto5f713f59_userpool_5f713f59"
      },
      "lastPushTimeStamp": "2023-09-01T21:24:42.713Z",
      "providerMetadata": {
        "s3TemplateURL": "https://s3.amazonaws.com/amplify-pronto-dev-163054-deployment/amplify-cfn-templates/auth/pronto5f713f59-cloudformation-template.json",
        "logicalId": "authpronto5f713f59"
      }
    },
    "userPoolGroups": {
      "dependsOn": [
        {
          "category": "auth",
          "resourceName": "pronto5f713f59",
          "attributes": [
            "UserPoolId",
            "AppClientIDWeb",
            "AppClientID",
            "IdentityPoolId"
          ]
        }
      ],
      "providerPlugin": "awscloudformation",
      "service": "Cognito-UserPool-Groups",
      "output": {
        "studentUserGroupGroupRole": "arn:aws:iam::915206092794:role/us-east-1_0MFceeZ4B-studentUserGroupGroupRole",
        "adminUserGroupGroupRole": "arn:aws:iam::915206092794:role/us-east-1_0MFceeZ4B-adminUserGroupGroupRole",
        "lecturerUserGroupGroupRole": "arn:aws:iam::915206092794:role/us-east-1_0MFceeZ4B-lecturerUserGroupGroupRole"
      },
      "lastPushTimeStamp": "2023-09-01T21:24:48.018Z",
      "providerMetadata": {
        "s3TemplateURL": "https://s3.amazonaws.com/amplify-pronto-dev-163054-deployment/amplify-cfn-templates/auth/userPoolGroups-cloudformation-template.json",
        "logicalId": "authuserPoolGroups"
      }
    }
  },
  "function": {
    "AdminQueries7f7a03b0": {
      "build": true,
      "dependsOn": [
        {
          "attributes": [
            "UserPoolId"
          ],
          "category": "auth",
          "resourceName": "pronto5f713f59"
        }
      ],
      "providerPlugin": "awscloudformation",
      "service": "Lambda",
      "output": {
        "LambdaExecutionRoleArn": "arn:aws:iam::915206092794:role/AdminQueries7f7a03b0LambdaRole-dev",
        "Region": "us-east-1",
        "Arn": "arn:aws:lambda:us-east-1:915206092794:function:AdminQueries7f7a03b0-dev",
        "Name": "AdminQueries7f7a03b0-dev",
        "LambdaExecutionRole": "AdminQueries7f7a03b0LambdaRole-dev"
      },
      "lastPushTimeStamp": "2023-09-01T21:24:42.715Z",
      "providerMetadata": {
        "s3TemplateURL": "https://s3.amazonaws.com/amplify-pronto-dev-163054-deployment/amplify-cfn-templates/function/AdminQueries7f7a03b0-cloudformation-template.json",
        "logicalId": "functionAdminQueries7f7a03b0"
      },
      "s3Bucket": {
        "deploymentBucketName": "amplify-pronto-dev-163054-deployment",
        "s3Key": "amplify-builds/AdminQueries7f7a03b0-4977306a6a7435714749-build.zip"
      }
    },
    "pronto5f713f59PostAuthentication": {
      "build": true,
      "providerPlugin": "awscloudformation",
      "service": "Lambda",
      "output": {
        "LambdaExecutionRoleArn": "arn:aws:iam::915206092794:role/pronto5f713f59PostAuthentication-dev",
        "Region": "us-east-1",
        "Arn": "arn:aws:lambda:us-east-1:915206092794:function:pronto5f713f59PostAuthentication-dev",
        "Name": "pronto5f713f59PostAuthentication-dev",
        "LambdaExecutionRole": "pronto5f713f59PostAuthentication-dev"
      },
      "lastPushTimeStamp": "2023-09-01T21:24:42.716Z",
      "providerMetadata": {
        "s3TemplateURL": "https://s3.amazonaws.com/amplify-pronto-dev-163054-deployment/amplify-cfn-templates/function/pronto5f713f59PostAuthentication-cloudformation-template.json",
        "logicalId": "functionpronto5f713f59PostAuthentication"
      },
      "s3Bucket": {
        "deploymentBucketName": "amplify-pronto-dev-163054-deployment",
        "s3Key": "amplify-builds/pronto5f713f59PostAuthentication-646a387935642f586647-build.zip"
      }
    },
    "pronto5f713f59PreSignup": {
      "build": true,
      "providerPlugin": "awscloudformation",
      "service": "Lambda",
      "output": {
        "LambdaExecutionRoleArn": "arn:aws:iam::915206092794:role/pronto5f713f59PreSignup-dev",
        "Region": "us-east-1",
        "Arn": "arn:aws:lambda:us-east-1:915206092794:function:pronto5f713f59PreSignup-dev",
        "Name": "pronto5f713f59PreSignup-dev",
        "LambdaExecutionRole": "pronto5f713f59PreSignup-dev"
      },
      "lastPushTimeStamp": "2023-09-01T21:24:42.717Z",
      "providerMetadata": {
        "s3TemplateURL": "https://s3.amazonaws.com/amplify-pronto-dev-163054-deployment/amplify-cfn-templates/function/pronto5f713f59PreSignup-cloudformation-template.json",
        "logicalId": "functionpronto5f713f59PreSignup"
      },
      "s3Bucket": {
        "deploymentBucketName": "amplify-pronto-dev-163054-deployment",
        "s3Key": "amplify-builds/pronto5f713f59PreSignup-564437393153796d4474-build.zip"
      }
    }
  },
  "storage": {
    "prontoBlobeStore": {
      "dependsOn": [
        {
          "category": "auth",
          "resourceName": "pronto5f713f59",
          "attributes": [
            "UserPoolId"
          ]
        },
        {
          "category": "auth",
          "resourceName": "userPoolGroups",
          "attributes": [
            "adminUserGroupGroupRole"
          ]
        },
        {
          "category": "auth",
          "resourceName": "userPoolGroups",
          "attributes": [
            "lecturerUserGroupGroupRole"
          ]
        },
        {
          "category": "auth",
          "resourceName": "userPoolGroups",
          "attributes": [
            "studentUserGroupGroupRole"
          ]
        }
      ],
      "providerPlugin": "awscloudformation",
      "service": "S3",
      "output": {
        "BucketName": "pronto-storage-bucket163054-dev",
        "Region": "us-east-1"
      },
      "lastPushTimeStamp": "2023-09-01T21:24:48.134Z",
      "providerMetadata": {
        "s3TemplateURL": "https://s3.amazonaws.com/amplify-pronto-dev-163054-deployment/amplify-cfn-templates/storage/cloudformation-template.json",
        "logicalId": "storageprontoBlobeStore"
      }
    }
  }
}